{
  "_fv": 33,
  "_type": "tool",
  "definition": {
    "renderType": 0,
    "texture": "sledgehammer",
    "customModelName": "Normal",
    "name": "Sledgehammer",
    "specialInfo": [],
    "creativeTab": {
      "value": "CUSTOM:Wastelandersitems"
    },
    "toolType": "Pickaxe",
    "harvestLevel": 1,
    "efficiency": 4.5,
    "attackSpeed": 0.19999999999999998,
    "enchantability": 2,
    "damageVsEntity": 7.0,
    "usageCount": 200,
    "blocksAffected": [],
    "hasGlow": false,
    "repairItems": [
      {
        "value": "CUSTOM:Steelingot"
      }
    ],
    "immuneToFire": false,
    "stayInGridWhenCrafting": false,
    "damageOnCrafting": true
  }
}